{
 "action": "Create Entry",
 "creation": "2025-01-07 16:54:31.334026",
 "description": "Seg\u00fan la fecha de nacimiento se deber\u00e1 tener en cuenta el tipo de identificaci\u00f3n del usuario de la siguiente manera:\r\n\r\nSi el usuario tiene 6 a\u00f1os o menos, el tipo de documento debe ser \"Registro civil\", \r\nsi no cuenta con este documento y si tiene tres a\u00f1os o menos, se puede registrar \"Certificado de nacido vivo\", \r\nsi no cuenta con este documento, se puede registrar \"Pasaporte\",\r\nsi no cuenta con este documento,\r\nse puede registrar \"Carn\u00e9 diplom\u00e1tico\" o \"salvoconducto de permanencia\" o permiso especial de permanencia\" o \"documento extranjero\" o \"permiso temporal de permanencia\",\r\nsi no cuenta con ninguno de estos documentos, se puede registrar \"Menor sin identificar\".\r\n\r\nSi el usuario tiene entre 7 y 17 a\u00f1os , el tipo de documento debe ser \"Tarjeta de identidad\",\r\nsi no cuenta con este documento se puede registrar \"C\u00e9dula de extranjer\u00eda\", \r\nsi no cuenta con este documento se puede registrar \"Pasaporte\",\r\nsi no cuenta con este documento\r\nse puede registrar \"Carn\u00e9 diplom\u00e1tico\" o \"salvoconducto de permanencia\" o permiso especial de permanencia\" o \"documento extranjero\" o \"permiso temporal de permanencia\",\r\nsi no cuenta con ninguno de estos documentos, se puede registrar \"Menor sin identificar\".\r\n\r\nSi el usuario tiene 18 a\u00f1os o m\u00e1s, el tipo de documento debe ser \"C\u00e9dula de ciudadan\u00eda\",\r\nsi no cuenta con este documento y si tiene hasta 19 a\u00f1os se puede registrar \"Tarjeta de identidad\",\r\nsi no cuenta con este documento se puede registrar \"C\u00e9dula de extranjer\u00eda\",\r\nsi no cuenta con este documento se puede registrar \"Pasaporte\",\r\nsi no cuenta con este documento\r\nse puede registrar \"Carn\u00e9 diplom\u00e1tico\" o \"salvoconducto de permanencia\" permiso especial de permanencia\" o \"documento extranjero\" o \"permiso temporal de permanencia\",\r\nsi no cuenta con ninguno de estos documentos, se puede registrar \"Adulto sin identificar\".\r\n\r\nSi se informan datos de reci\u00e9n nacido, el usuario puede tener entre 9 a 60 a\u00f1os.",
 "docstatus": 0,
 "doctype": "Onboarding Step",
 "idx": 0,
 "is_complete": 0,
 "is_single": 0,
 "is_skipped": 0,
 "modified": "2025-01-07 16:54:31.334026",
 "modified_by": "Administrator",
 "name": "Register Patient",
 "owner": "Administrator",
 "reference_document": "Patient",
 "show_form_tour": 0,
 "show_full_form": 0,
 "title": "Register Patient",
 "validate_action": 1
}